microsoft/teams/common/__init__.py
microsoft/teams/common/events/__init__.py
microsoft/teams/common/events/event_emitter.py
microsoft/teams/common/http/__init__.py
microsoft/teams/common/http/client.py
microsoft/teams/common/http/client_token.py
microsoft/teams/common/http/interceptor.py
microsoft/teams/common/logging/__init__.py
microsoft/teams/common/logging/ansi.py
microsoft/teams/common/logging/console.py
microsoft/teams/common/logging/filter.py
microsoft/teams/common/logging/formatter.py
microsoft/teams/common/storage/__init__.py
microsoft/teams/common/storage/list_local_storage.py
microsoft/teams/common/storage/local_storage.py
microsoft/teams/common/storage/storage.py
microsoft_teams_common-2.0.0a5.dist-info/METADATA
microsoft_teams_common-2.0.0a5.dist-info/WHEEL
microsoft_teams_common-2.0.0a5.dist-info/RECORD
